[
  {
    "run_a": "2026-05-09-00_24_28",
    "run_b": "2026-05-09-00_35_24",
    "parameter_l2_distance": "26.49199867",
    "parameter_cosine_similarity": "-0.003578615841",
    "prediction_mse": "1.141830944e-05",
    "test_mse_run_a": "0.00017297882",
    "test_mse_run_b": "0.0001522244711"
  },
  {
    "run_a": "2026-05-09-00_24_28",
    "run_b": "2026-05-09-00_46_10",
    "parameter_l2_distance": "26.01350975",
    "parameter_cosine_similarity": "0.01701289974",
    "prediction_mse": "1.375232114e-05",
    "test_mse_run_a": "0.00017297882",
    "test_mse_run_b": "0.0001787812507"
  },
  {
    "run_a": "2026-05-09-00_35_24",
    "run_b": "2026-05-09-00_46_10",
    "parameter_l2_distance": "26.13223839",
    "parameter_cosine_similarity": "0.01093652379",
    "prediction_mse": "1.43503039e-05",
    "test_mse_run_a": "0.0001522244711",
    "test_mse_run_b": "0.0001787812507"
  }
]